ordec/__init__.py
ordec/extlibrary.py
ordec/importer.py
ordec/language.py
ordec/render.py
ordec/server.py
ordec/sphinx_ext.py
ordec/version.py
ordec/webdist.tar
ordec/core/__init__.py
ordec/core/cell.py
ordec/core/constraints.py
ordec/core/directory.py
ordec/core/geoprim.py
ordec/core/ordb.py
ordec/core/rational.py
ordec/core/schema.py
ordec/layout/__init__.py
ordec/layout/gds_in.py
ordec/layout/gds_out.py
ordec/layout/helpers.py
ordec/layout/klayout.py
ordec/layout/makevias.py
ordec/layout/webdata.py
ordec/lib/__init__.py
ordec/lib/base.py
ordec/lib/generic_mos.py
ordec/lib/ihp130.py
ordec/lib/pdk_common.py
ordec/lib/schem_sim_test.py
ordec/lib/sky130.py
ordec/lib/test.py
ordec/lib/examples/__init__.py
ordec/lib/examples/blank.py
ordec/lib/examples/blank.uistate.json
ordec/lib/examples/currentmirror.ord
ordec/lib/examples/diffpair.ord
ordec/lib/examples/diffpair.uistate.json
ordec/lib/examples/nand2.ord
ordec/lib/examples/nand2.uistate.json
ordec/lib/examples/voltagedivider.ord
ordec/lib/examples/voltagedivider.uistate.json
ordec/lib/examples/voltagedivider_py.py
ordec/lib/examples/voltagedivider_py.uistate.json
ordec/lib/ord1_test/__init__.py
ordec/lib/ord1_test/d_ff_soc.ord
ordec/lib/ord1_test/d_flip_flop.ord
ordec/lib/ord1_test/d_latch.ord
ordec/lib/ord1_test/d_latch_schem_check.ord
ordec/lib/ord1_test/d_latch_soc.ord
ordec/lib/ord1_test/empty.ord
ordec/lib/ord1_test/empty2.ord
ordec/lib/ord1_test/inv_all_features.ord
ordec/lib/ord1_test/inv_for_loop.ord
ordec/lib/ord1_test/inv_liop.ord
ordec/lib/ord1_test/inv_origin_centered.ord
ordec/lib/ord1_test/inv_structured.ord
ordec/lib/ord1_test/inv_with_pos.ord
ordec/lib/ord1_test/multicell.ord
ordec/lib/ord1_test/mux2_structured.ord
ordec/lib/ord1_test/nand.ord
ordec/lib/ord1_test/nand_structured.ord
ordec/lib/ord1_test/net_definition.ord
ordec/lib/ord1_test/resdiv_flat_tb.ord
ordec/lib/ord1_test/ringosc.ord
ordec/lib/ord1_test/ringosc_liop.ord
ordec/lib/ord1_test/ringosc_structured.ord
ordec-0.3.0.dist-info/licenses/REUSE.toml
ordec-0.3.0.dist-info/licenses/LICENSES/Apache-2.0.txt
ordec-0.3.0.dist-info/licenses/LICENSES/CC0-1.0.txt
ordec-0.3.0.dist-info/licenses/LICENSES/OFL-1.1.txt
ordec-0.3.0.dist-info/METADATA
ordec-0.3.0.dist-info/WHEEL
ordec-0.3.0.dist-info/entry_points.txt
ordec-0.3.0.dist-info/top_level.txt
ordec-0.3.0.dist-info/RECORD
