Metadata-Version: 2.4
Name: ordec
Version: 0.3.0
Summary: ORDeC
Maintainer-email: Tobias Kaiser <kaiser@tu-berlin.de>
License-Expression: Apache-2.0
Project-URL: Homepage, https://github.com/tub-msc/ordec
Project-URL: Documentation, https://ordec.readthedocs.io
Classifier: Programming Language :: Python :: 3
Requires-Python: >=3.6
License-File: REUSE.toml
License-File: LICENSES/Apache-2.0.txt
License-File: LICENSES/OFL-1.1.txt
License-File: LICENSES/CC0-1.0.txt
Requires-Dist: pyrsistent>=0.18.1
Requires-Dist: lark>=1.1.5
Requires-Dist: astor>=0.8.1
Requires-Dist: numpy>=1.24.2
Requires-Dist: scipy>=1.10.1
Requires-Dist: atpublic>=6.0.1
Requires-Dist: websockets>=15.0.1
Requires-Dist: tabulate>=0.8.9
Requires-Dist: inotify-simple>=1.3.0
Requires-Dist: python-gdsii>=0.2.1
Provides-Extra: test
Requires-Dist: pytest>=7.2.1; extra == "test"
Requires-Dist: pytest-cov>=4.0.0; extra == "test"
Requires-Dist: selenium>=4.8.3; extra == "test"
Requires-Dist: pillow>=11.1.0; extra == "test"
Provides-Extra: extra
Requires-Dist: black>=23.1.0; extra == "extra"
Dynamic: license-file
